examples/dummy/generate_data_card.py
tests/test_data_card.py
tsq/data_card.py
tsq_lib-0.2.1.dist-info/licenses/LICENSE
tsq_lib-0.2.1.dist-info/METADATA
tsq_lib-0.2.1.dist-info/WHEEL
tsq_lib-0.2.1.dist-info/top_level.txt
tsq_lib-0.2.1.dist-info/RECORD
