Metadata-Version: 2.4
Name: tsq-lib
Version: 0.2.1
Summary: time series quality library
Author-email: Mathis Jander <mathis.jander@utwente.nl>
License: MIT
Project-URL: Homepage, https://github.com/MSCA-DN-Digital-Finance/tsq
Classifier: Programming Language :: Python :: 3
Classifier: License :: OSI Approved :: MIT License
Classifier: Operating System :: OS Independent
Requires-Python: >=3.9
License-File: LICENSE
Requires-Dist: pandas
Dynamic: license-file
